gys/Api_Allocate.py
gys/Api_Audit.py
gys/Api_BatchSave.py
gys/Api_BatchSaveQuery.py
gys/Api_Delete.py
gys/Api_ExecuteBillQuery.py
gys/Api_ExecuteOperation.py
gys/Api_GetDataCenters.py
gys/Api_Save.py
gys/Api_Submit.py
gys/Api_UnAudit.py
gys/Api_View.py
gys/__init__.py
pysupplier/__init__.py
pysupplier/text3.py
pysupplier-1.0.3.dist-info/METADATA
pysupplier-1.0.3.dist-info/WHEEL
pysupplier-1.0.3.dist-info/top_level.txt
pysupplier-1.0.3.dist-info/RECORD
