Metadata-Version: 2.1
Name: pysupplier
Version: 1.0.3
Summary: reshape data type in py language 
Home-page: http://www.reshapedata.com
Author: yuyang
Author-email: 958460064@qq.com
License: Apache License
Keywords: reshapedata,rdt,pyrdt
Requires-Python: >=3.6
Requires-Dist: requests
